MANIFEST.in
README.rst
setup.py
aliyun_python_sdk_baas.egg-info/PKG-INFO
aliyun_python_sdk_baas.egg-info/SOURCES.txt
aliyun_python_sdk_baas.egg-info/dependency_links.txt
aliyun_python_sdk_baas.egg-info/requires.txt
aliyun_python_sdk_baas.egg-info/top_level.txt
aliyunsdkbaas/__init__.py
aliyunsdkbaas/endpoint.py
aliyunsdkbaas/request/__init__.py
aliyunsdkbaas/request/v20180731/AcceptEthereumInvitationRequest.py
aliyunsdkbaas/request/v20180731/AcceptInvitationRequest.py
aliyunsdkbaas/request/v20180731/AddEthereumNodeRequest.py
aliyunsdkbaas/request/v20180731/AddFabricExternalOrganizationToChannelRequest.py
aliyunsdkbaas/request/v20180731/AddFabricOrganizationToExternalChannelRequest.py
aliyunsdkbaas/request/v20180731/ApplyAntChainCertificateRequest.py
aliyunsdkbaas/request/v20180731/ApplyAntChainCertificateWithKeyAutoCreationRequest.py
aliyunsdkbaas/request/v20180731/ApplyAntChainRequest.py
aliyunsdkbaas/request/v20180731/ApplyAntChainWithKeyAutoCreationRequest.py
aliyunsdkbaas/request/v20180731/ApplyBlockchainRequest.py
aliyunsdkbaas/request/v20180731/ApplyBlockchainWithKeyAutoCreationRequest.py
aliyunsdkbaas/request/v20180731/ApplyPublicAntChainRequest.py
aliyunsdkbaas/request/v20180731/ApplyPublicAntChainWithKeyAutoCreationRequest.py
aliyunsdkbaas/request/v20180731/ApproveEthereumInviteeRequest.py
aliyunsdkbaas/request/v20180731/BatchAddAntChainMiniAppQRCodeAuthorizedUsersRequest.py
aliyunsdkbaas/request/v20180731/BindFabricManagementChaincodeRequest.py
aliyunsdkbaas/request/v20180731/CheckConsortiumDomainRequest.py
aliyunsdkbaas/request/v20180731/CheckOrganizationDomainRequest.py
aliyunsdkbaas/request/v20180731/ConfirmConsortiumMemberRequest.py
aliyunsdkbaas/request/v20180731/CopyAntChainContractProjectRequest.py
aliyunsdkbaas/request/v20180731/CreateAccessTokenRequest.py
aliyunsdkbaas/request/v20180731/CreateAccountRequest.py
aliyunsdkbaas/request/v20180731/CreateAccountWithKeyPairAutoCreationRequest.py
aliyunsdkbaas/request/v20180731/CreateAntChainAccountRequest.py
aliyunsdkbaas/request/v20180731/CreateAntChainAccountWithKeyPairAutoCreationRequest.py
aliyunsdkbaas/request/v20180731/CreateAntChainConsortiumRequest.py
